{"createdAt":"2025-08-11T09:21:50.816Z","updatedAt":"2025-08-18T10:47:20.000Z","id":"qD5TPeIHiHQQtGTK","name":"Amir-Shipping-Get","active":false,"isArchived":false,"nodes":[{"parameters":{"url":"=https://shipsgo.com/api/v1.1/ContainerService/GetContainerInfo/","sendQuery":true,"queryParameters":{"parameters":[{"name":"authCode","value":"78e3642bec2adb856211df1ef7429604"},{"name":"requestId","value":"=5005540"}]},"sendHeaders":true,"headerParameters":{"parameters":[{"name":"Accept","value":"application/json"}]},"options":{}},"type":"n8n-nodes-base.httpRequest","typeVersion":4.2,"position":[0,0],"id":"59c43443-1f2d-41b1-bf69-4238266321a4","name":"Get Shipping Info from ShipsGo2","alwaysOutputData":true,"onError":"continueRegularOutput"},{"parameters":{},"type":"n8n-nodes-base.manualTrigger","typeVersion":1,"position":[-240,0],"id":"028bf5f6-ed72-485a-be5c-b25063977ef2","name":"When clicking ‘Execute workflow’"},{"parameters":{"jsCode":"// Loop over input items and add a new field called 'myNewField' to the JSON of each one\nfor (const item of $input.all()) {\n  item.json.myNewField = 1;\n}\n\nreturn $input.all();"},"type":"n8n-nodes-base.code","typeVersion":2,"position":[256,0],"id":"d5be2ca2-4416-4c08-8e77-33236f67c74d","name":"Code"}],"connections":{"When clicking ‘Execute workflow’":{"main":[[{"node":"Get Shipping Info from ShipsGo2","type":"main","index":0}]]},"Get Shipping Info from ShipsGo2":{"main":[[{"node":"Code","type":"main","index":0}]]}},"settings":{"executionOrder":"v1"},"staticData":null,"meta":null,"pinData":{},"versionId":"87dd4164-0552-4682-b7f1-4ad003dd187b","triggerCount":0,"tags":[]}